{
  "jungle": [
    "Aatrox",
    "Amumu",
    "Camille",
    "DrMundo",
    "Ekko",
    "Elise",
    "Evelynn",
    "Fiddlesticks",
    "Gragas",
    "Graves",
    "Hecarim",
    "Ivern",
    "JarvanIV",
    "Jax",
    "Karthus",
    "Kayn",
    "Khazix",
    "Kindred",
    "Lee Sin",
    "MasterYi",
    "Nidalee",
    "Nocturne",
    "Nunu",
    "Olaf",
    "Pantheon",
    "Poppy",
    "Qiyana",
    "Rammus",
    "RekSai",
    "Rengar",
    "Sejuani",
    "Shaco",
    "Shyvana",
    "Skarner",
    "Sylas",
    "Taliyah",
    "Udyr",
    "Vi",
    "Volibear",
    "Warwick",
    "Wukong",
    "XinZhao",
    "Zac"
  ],
  "mid": ["Annie", "Syndra", "Katarina"],
  "top": ["Darius", "Garen"],
  "sup": [
    "Alistar",
    "Bard",
    "Brand",
    "Braum",
    "Fiddlesticks",
    "Galio",
    "Gragas",
    "Janna",
    "Karma",
    "Leona",
    "Lulu",
    "Lux",
    "Malphite",
    "Maokai",
    "MissFortune",
    "Morgana",
    "Nami",
    "Nautilus",
    "Neeko",
    "Poppy",
    "Pyke",
    "Rakan",
    "Senna",
    "Shaco",
    "Shen",
    "Sona",
    "Soraka",
    "Swain",
    "TahmKench",
    "Taric",
    "Thresh",
    "Veigar",
    "VelKoz",
    "Volibear",
    "Xerath",
    "Yuumi",
    "Zac",
    "Zilean",
    "Zyra"
  ],
  "adc": [
    "Ashe",
    "Caitlyn",
    "Draven",
    "Ezreal",
    "Hermerdinger",
    "Jhin",
    "Jinx",
    "Kaisa",
    "Kalista",
    "KogMaw",
    "Lucian",
    "MissFortune",
    "Senna",
    "Sivir",
    "Swain",
    "Tristana",
    "Twitch",
    "Varus",
    "Vayne",
    "Xayah",
    "Yasuo"
  ]
}
